Workbook

Sheet Listas
A1: Status | B1: Criticidade | C1: Ocupação | D1: Conservação | E1: Liquidez | F1: Risco jurídico | G1: SimNão | H1: Cenário
A2: OK | B2: Crítico | C2: Desocupado | D2: Excelente | E2: Alta | F2: Muito baixo | G2: Sim | H2: Pessimista
A3: Pendente | B3: Importante | C3: Saída amigável provável | D3: Bom | E3: Média | F3: Baixo | G3: Não | H3: Base
A4: Problema | B4: Desejável | C4: Ocupado - incerto | D4: Regular | E4: Baixa | F4: Médio | G4: A confirmar | H4: Otimista
A5: N/A | C5: Litígio/resistência | D5: Ruim | F5: Alto

Sheet Guia
A1: GUIA RÁPIDO — ANÁLISE DE IMÓVEIS EM LEILÃO
A3: COMO USAR
A4: 1 | B4: Preencha somente as células amarelas com fonte azul.
A5: 2 | B5: Conclua a diligência. Itens críticos pendentes ou com problema bloqueiam o lance.
A6: 3 | B6: Valide valor de mercado com comparáveis reais e orçamento de reforma.
A7: 4 | B7: Consulte Score e Dashboard antes de definir o lance.
A8: 5 | B8: Nunca ultrapasse o Lance Máximo Recomendado.
A10: LEGENDA
A11: Cor | B11: Significado | C11: Ação | D11: Exemplo
A12: Amarelo / azul | B12: Entrada do usuário | C12: Preencher ou validar | D12: Preço, prazo, status
A13: Branco / preto | B13: Fórmula | C13: Não alterar | D13: ROI, lucro, lance máximo
A14: Verde | B14: Referência entre abas | C14: Calculado automaticamente | D14: Valor de mercado validado
A15: AVISO IMPORTANTE
A16: Esta planilha é ferramenta de apoio e não substitui parecer de advogado imobiliário, contador, corretor e engenheiro.
A17: Quando houver ônus, ocupação, processo, irregularidade ou dúvida no edital, não dê lance sem validação profissional.

Sheet Entradas
A1: ENTRADAS DO INVESTIMENTO — JUNDIAÍ
A3: IDENTIFICAÇÃO DO IMÓVEL
A4: Campo | B4: Valor | C4: Unidade / opção | D4: Fonte / evidência | E4: Data da consulta | F4: Validado?
A5: Nome da oportunidade | B5: Jundiaí - Recanto Quarto Centenário | D5: Planilha original | F5: Sim
A6: Endereço / condomínio | B6: Condomínio Residencial Begônias | D6: Matrícula 146.062 | F6: Sim
A7: Tipo de leilão | B7: Extrajudicial - Caixa | D7: Edital 0018/0326-CPVE/RE | F7: Sim
A8: Metragem privativa | B8: 50.56 | C8: m² | D8: Matrícula 146.062 | F8: Sim
A9: Modalidade de pagamento | B9: À vista | D9: Edital | F9: Sim
A10: Cenário selecionado | B10: Base | D10: Escolha do investidor | F10: Sim
A12: PREMISSAS FINANCEIRAS
A13: Premissa | B13: Valor | C13: Unidade | D13: Fonte / observação | E13: Data | F13: Validado?
A14: Valor da arrematação | B14: 163056.69 | C14: R$ | D14: Edital / proposta | F14: Sim
A15: Comissão do leiloeiro | B15: 0.05 | C15: % do lance | D15: Edital | F15: Sim
A16: ITBI | B16: 0.03 | C16: % do lance | D16: Estimativa municipal; confirmar | F16: A confirmar
A17: Registro e escritura | B17: 3800 | C17: R$ | D17: Estimativa; confirmar cartório | F17: A confirmar
A18: Honorários jurídicos | B18: 5000 | C18: R$ | D18: Reserva para posse/desocupação | F18: A confirmar
A19: Reserva para certidões/documentos | B19: 1500 | C19: R$ | D19: Estimativa | F19: A confirmar
A20: Condomínio mensal | B20: 350 | C20: R$/mês | D20: Planilha original | F20: A confirmar
A21: IPTU mensal | B21: 80 | C21: R$/mês | D21: Planilha original | F21: A confirmar
A22: Seguro/manutenção mensal | B22: 100 | C22: R$/mês | D22: Estimativa | F22: A confirmar
A23: Prazo até posse | B23: 4 | C23: meses | D23: Cenário-base | F23: A confirmar
A24: Prazo de reforma | B24: 2 | C24: meses | D24: Estimativa | F24: A confirmar
A25: Prazo de venda após reforma | B25: 6 | C25: meses | D25: Estimativa | F25: A confirmar
... A29: Taxa mínima de atratividade | B29: 0.12 | C29: % a.a. | D29: Comparação com alternativa de investimento | F29: A confirmar

Sheet Diligencia
A1: DILIGÊNCIA E BLOQUEIOS
A3: # | B3: Categoria | C3: Verificação | D3: Criticidade | E3: Status | F3: Bloqueia lance? | G3: Responsável | H3: Data | I3: Evidência / fonte | J3: Impacto / observação
A4: 1 | B4: Edital | C4: Ler integralmente edital e anexos | D4: Crítico | E4: OK | F4: Sim | I4: Edital 0018/0326-CPVE/RE | J4: Venda AS-IS; pagamento à vista
A5: 2 | B5: Edital | C5: Confirmar desistência, multa e perda de valores | D5: Crítico | E5: Pendente | F5: Sim
A6: 3 | B6: Matrícula | C6: Obter matrícula atualizada há menos de 30 dias | D6: Crítico | E6: OK | F6: Sim | I6: Matrícula 146.062
A7: 4 | B7: Matrícula | C7: Validar penhora e procedimento de baixa | D7: Crítico | E7: Problema | F7: Sim | I7: Av.07/2022 | J7: Penhora condominial sem cancelamento identificado
A8: 5 | B8: Matrícula | C8: Verificar restrições MCMV ou outras | D8: Importante | E8: Pendente | F8: Não
A9: 6 | B9: Certidões | C9: Ações reais/reipersecutórias | D9: Importante | E9: Pendente | F9: Não
A10: 7 | B10: Ocupação | C10: Confirmar se está ocupado | D10: Crítico | E10: Pendente | F10: Sim
A11: 8 | B11: Ocupação | C11: Identificar ocupante e vínculo | D11: Crítico | E11: Pendente | F11: Sim
A12: 9 | B12: Ocupação | C12: Estimar prazo e custo da posse | D12: Importante | E12: Pendente | F12: Não
A13: 10 | B13: Débitos | C13: Obter saldo atualizado do condomínio | D13: Crítico | E13: Problema | F13: Sim | J13: Penhora indica dívida
A14: 11 | B14: Débitos | C14: Obter certidão de IPTU | D14: Crítico | E14: Pendente | F14: Sim
A15: 12 | B15: Débitos | C15: Confirmar responsabilidade por cada débito | D15: Crítico | E15: OK | F15: Sim | I15: Edital | J15: Comprador até limite previsto
A16: 13 | B16: Físico | C16: Realizar visita ou inspeção técnica | D16: Crítico | E16: Pendente | F16: Sim
A17: 14 | B17: Físico | C17: Orçar reforma em três cenários | D17: Importante | E17: Pendente | F17: Não
A18: 15 | B18: Mercado | C18: Validar preço com pelo menos 5 comparáveis | D18: Crítico | E18: Pendente | F18: Sim
A19: 16 | B19: Mercado | C19: Validar liquidez e prazo médio de venda | D19: Importante | E19: Pendente | F19: Não
A20: 17 | B20: Financeiro | C20: Garantir capital e reserva de contingência | D20: Crítico | E20: Pendente | F20: Sim
A21: 18 | B21: Tributário | C21: Validar tributação com contador | D21: Importante | E21: Pendente | F21: Não
A24: RESUMO AUTOMÁTICO
A25: Indicador | B25: Resultado
A26: Itens críticos pendentes | B26: =COUNTIFS($D$4:$D$21,"Crítico",$E$4:$E$21,"Pendente")
A27: Itens críticos com problema | B27: =COUNTIFS($D$4:$D$21,"Crítico",$E$4:$E$21,"Problema")
A28: Bloqueios ativos | B28: =COUNTIFS($F$4:$F$21,"Sim",$E$4:$E$21,"<>OK",$E$4:$E$21,"<>N/A")
A29: Diligência concluída? | B29: =IF(B28=0,"SIM","NÃO")
A30: Status para lance | B30: =IF(B28>0,"NÃO DAR LANCE","LIBERADO PARA ANÁLISE FINANCEIRA")

Sheet Debitos
A1: DÉBITOS, ÔNUS E OBRIGAÇÕES
A3: Tipo | B3: Valor apurado | C3: Responsável provável | D3: Limite/cobertura do edital | E3: Coberto por terceiro? | F3: Custo do comprador | G3: Status | H3: Fonte | I3: Observação
A4: Condomínio vencido | B4: 0 | C4: A confirmar | D4: Até limite do edital | E4: A confirmar | F4: =IF(OR(E4="Sim",G4="N/A"),0,B4) | G4: Pendente | H4: Administradora | I4: Penhora existente; obter saldo
A5: IPTU vencido | B5: 0 | C5: A confirmar | D5: Até limite do edital | E5: A confirmar | F5: =IF(OR(E5="Sim",G5="N/A"),0,B5) | G5: Pendente | H5: Prefeitura | I5: Obter certidão
A6: Água | B6: 0 | C6: A confirmar | D6: Não informado | E6: Não | F6: =IF(OR(E6="Sim",G6="N/A"),0,B6) | G6: Pendente | H6: Concessionária
A7: Energia | B7: 0 | C7: A confirmar | D7: Não informado | E7: Não | F7: =IF(OR(E7="Sim",G7="N/A"),0,B7) | G7: Pendente | H7: Concessionária
A8: Gás | B8: 0 | C8: A confirmar | D8: Não informado | E8: Não | F8: =IF(OR(E8="Sim",G8="N/A"),0,B8) | G8: N/A
A9: Multas condominiais | B9: 0 | C9: A confirmar | D9: A confirmar | E9: A confirmar | F9: =IF(OR(E9="Sim",G9="N/A"),0,B9) | G9: Pendente | H9: Administradora
A10: Custas para baixa de ônus | B10: 0 | C10: Comprador | D10: Não informado | E10: Não | F10: =IF(OR(E10="Sim",G10="N/A"),0,B10) | G10: Pendente | H10: Cartório/advogado
A11: Outros | B11: 0 | C11: Comprador | D11: Não | E11: Não | F11: =IF(OR(E11="Sim",G11="N/A"),0,B11) | G11: N/A
A13: RESUMO
A14: Total apurado | B14: =SUM(B4:B11)
A15: Total assumido pelo comprador | B15: =SUM(F4:F11)
A16: Débitos pendentes de apuração | B16: =COUNTIF(G4:G11,"Pendente")

Sheet Comparaveis
A1: COMPARÁVEIS DE MERCADO
A3: # | B3: Imóvel / link | C3: Bairro/condomínio | D3: Área m² | E3: Preço anunciado | F3: Desconto estimado | G3: Preço ajustado | H3: R$/m² ajustado | I3: Estado | J3: Data | K3: Fonte | L3: Usar?
A4: 1 | E4: 0 | F4: 0.05 | G4: =E4*(1-F4) | H4: =IFERROR(G4/D4,0) | L4: Não
A5: 2 | E5: 0 | F5: 0.05 | G5: =E5*(1-F5) | H5: =IFERROR(G5/D5,0) | L5: Não
A6: 3 | E6: 0 | F6: 0.05 | G6: =E6*(1-F6) | H6: =IFERROR(G6/D6,0) | L6: Não
A7: 4 | E7: 0 | F7: 0.05 | G7: =E7*(1-F7) | H7: =IFERROR(G7/D7,0) | L7: Não
A8: 5 | E8: 0 | F8: 0.05 | G8: =E8*(1-F8) | H8: =IFERROR(G8/D8,0) | L8: Não
A9: 6 | E9: 0 | F9: 0.05 | G9: =E9*(1-F9) | H9: =IFERROR(G9/D9,0) | L9: Não
A10: 7 | E10: 0 | F10: 0.05 | G10: =E10*(1-F10) | H10: =IFERROR(G10/D10,0) | L10: Não
A11: 8 | E11: 0 | F11: 0.05 | G11: =E11*(1-F11) | H11: =IFERROR(G11/D11,0) | L11: Não
A12: 9 | E12: 0 | F12: 0.05 | G12: =E12*(1-F12) | H12: =IFERROR(G12/D12,0) | L12: Não
A13: 10 | E13: 0 | F13: 0.05 | G13: =E13*(1-F13) | H13: =IFERROR(G13/D13,0) | L13: Não
A15: VALOR DE MERCADO VALIDADO
A16: Indicador | B16: Resultado
A17: Quantidade utilizada | B17: =COUNTIF(L4:L13,"Sim")
A18: R$/m² médio | B18: =IFERROR(SUMIF(L4:L13,"Sim",H4:H13)/B17,0)
A19: R$/m² mediano | B19: =B18
A20: Valor de mercado estimado | B20: =B18*Entradas!B8
A21: Grau de confiança | B21: =IF(B17>=5,"ALTA",IF(B17>=3,"MÉDIA","BAIXA"))

Sheet Reforma
A1: ORÇAMENTO DE REFORMA — TRÊS CENÁRIOS
A3: Item | B3: Quantidade | C3: Unidade | D3: Custo unitário | E3: Leve | F3: Médio | G3: Pesado | H3: Fonte / observação
A4: Pintura | B4: 1 | C4: pacote | D4: 5000 | E4: 1 | F4: 1 | G4: 1 | H4: Estimativa
A5: Pisos/revestimentos | B5: 51 | C5: m² | D5: 120 | E5: 0 | F5: 0.5 | G5: 1
A6: Elétrica | B6: 1 | C6: pacote | D6: 6000 | E6: 0.1 | F6: 0.5 | G6: 1
A7: Hidráulica | B7: 1 | C7: pacote | D7: 7000 | E7: 0.1 | F7: 0.4 | G7: 1
A8: Cozinha | B8: 1 | C8: pacote | D8: 8000 | E8: 0.1 | F8: 0.5 | G8: 1
A9: Banheiro | B9: 1 | C9: pacote | D9: 7000 | E9: 0.1 | F9: 0.5 | G9: 1
A10: Portas/esquadrias | B10: 1 | C10: pacote | D10: 4000 | E10: 0.1 | F10: 0.4 | G10: 1
A11: Limpeza/caçamba | B11: 1 | C11: pacote | D11: 1500 | E11: 1 | F11: 1 | G11: 1
A12: Contingência | B12: 1 | C12: % | D12: 0.15 | E12: 0 | F12: 0 | G12: 0 | H12: Aplicada no resumo
A14: TOTAL POR CENÁRIO
A15: Cenário | B15: Subtotal | C15: Contingência | D15: Total
A16: Leve | B16: =SUMPRODUCT($B$4:$B$11,$D$4:$D$11,$E$4:$E$11) | C16: =B16*$D$12 | D16: =B16+C16
A17: Médio | B17: =SUMPRODUCT($B$4:$B$11,$D$4:$D$11,$F$4:$F$11) | C17: =B17*$D$12 | D17: =B17+C17
A18: Pesado | B18: =SUMPRODUCT($B$4:$B$11,$D$4:$D$11,$G$4:$G$11) | C18: =B18*$D$12 | D18: =B18+C18
A19: =Entradas!B10 | D19: =IF(A19="Pessimista",D18,IF(A19="Otimista",D16,D17))

Sheet Cenarios
A1: CENÁRIOS DE PREÇO, PRAZO E RISCO
A3: Premissa | B3: Pessimista | C3: Base | D3: Otimista | E3: Selecionado | F3: Unidade | G3: Fonte | H3: Observação
A4: Valor de mercado | B4: 245000 | C4: 266300 | D4: 280000 | E4: =IF(Entradas!B10="Pessimista",B4,IF(Entradas!B10="Otimista",D4,C4)) | F4: R$ | G4: Avaliação Caixa / validar comparáveis
A5: Desconto na venda | B5: 0.07 | C5: 0.03 | D5: 0.01 | E5: =IF(Entradas!B11="Pessimista",B5,IF(Entradas!B11="Otimista",D5,C5)) | F5: % | G5: Premissa
A6: Prazo até posse | B6: 10 | C6: 4 | D6: 1 | E6: =IF(Entradas!B12="Pessimista",B6,IF(Entradas!B12="Otimista",D6,C6)) | F6: meses | G6: Premissa
A7: Prazo de reforma | B7: 3 | C7: 2 | D7: 1 | E7: =IF(Entradas!B13="Pessimista",B7,IF(Entradas!B13="Otimista",D7,C7)) | F7: meses | G7: Premissa
A8: Prazo de venda | B8: 9 | C8: 6 | D8: 3 | E8: =IF(Entradas!B14="Pessimista",B8,IF(Entradas!B14="Otimista",D8,C8)) | F8: meses | G8: Premissa
A9: Reforma total | B9: =Reforma!D18 | C9: =Reforma!D17 | D9: =Reforma!D16 | E9: =IF(Entradas!B15="Pessimista",B9,IF(Entradas!B15="Otimista",D9,C9)) | F9: R$ | G9: Aba Reforma
A10: Débitos assumidos | B10: =Debitos!B15 | C10: =Debitos!B15 | D10: =Debitos!B15 | E10: =IF(Entradas!B16="Pessimista",B10,IF(Entradas!B16="Otimista",D10,C10)) | F10: R$ | G10: Aba Débitos
A11: Contingência jurídica | B11: 15000 | C11: 7000 | D11: 3000 | E11: =IF(Entradas!B17="Pessimista",B11,IF(Entradas!B17="Otimista",D11,C11)) | F11: R$ | G11: Premissa

Sheet Fluxo
A1: FLUXO DE CAIXA E RETORNO DO INVESTIMENTO
A3: RESUMO DO PROJETO
A4: Indicador | B4: Valor | C4: Unidade | D4: Observação
A5: Preço de venda anunciado | B5: =Cenarios!E4 | C5: R$ | D5: Cenário selecionado
A6: Preço efetivo de venda | B6: =B5*(1-Cenarios!E5) | C6: R$ | D6: Após desconto comercial
A7: Comissão corretor | B7: =B6*Entradas!B27 | C7: R$
A8: Receita líquida antes de imposto | B8: =B6-B7 | C8: R$
A9: Valor da arrematação | B9: =Entradas!B14 | C9: R$
A10: Comissão leiloeiro | B10: =B9*Entradas!B15 | C10: R$
A11: ITBI | B11: =B9*Entradas!B16 | C11: R$
A12: Registro/escritura | B12: =Entradas!B17 | C12: R$
A13: Honorários jurídicos | B13: =Entradas!B18 | C13: R$
A14: Certidões/documentos | B14: =Entradas!B19 | C14: R$
A15: Reforma | B15: =Cenarios!E9 | C15: R$
A16: Débitos assumidos | B16: =Cenarios!E10 | C16: R$
A17: Contingência jurídica | B17: =Cenarios!E11 | C17: R$
A18: Custo de carrego | B18: =(Entradas!B21+Entradas!B22+Entradas!B23)*(Cenarios!E6+Cenarios!E7+Cenarios!E8) | C18: R$
A19: Investimento total | B19: =SUM(B9:B18) | C19: R$
A20: Lucro antes de imposto | B20: =B8-B19 | C20: R$
A21: Imposto estimado | B21: =MAX(0,B20*Entradas!B28) | C21: R$
A22: Lucro líquido | B22: =B20-B21 | C22: R$
A24: INDICADORES
A25: Indicador | B25: Resultado | C25: Meta / referência | D25: Interpretação
A26: Prazo total | B26: =SUM(Cenarios!E6:E8) | C26: ≤ 12 meses
A27: Desconto bruto | B27: =IFERROR(1-Entradas!B14/B5,0) | C27: >= 30%
A28: Margem líquida | B28: =IFERROR(B22/B6,0) | C28: >= 15%
A29: ROI total | B29: =IFERROR(B22/B19,0) | C29: >= 20%
A30: ROI anualizado | B30: =IFERROR((1+B29)^(12/B26)-1,0) | C30: >= TMA
A31: Capital em risco | B31: =B19
A32: Lucro mínimo desejado | B32: =B31*((1+Entradas!B29)^(B26/12)-1)+0.15*B6
A33: Lance máximo recomendado | B33: =(B8-B12-B13-B14-B15-B16-B17-B18-B21-B32)/(1+Entradas!B15+Entradas!B16)
A34: Folga até o lance máximo | B34: =B33-Entradas!B14 | C34: > 0

Sheet Score
A1: SCORE DE RISCO E DECISÃO
A3: MOTOR DE BLOQUEIO
A4: Indicador | B4: Resultado | C4: Regra
A5: Bloqueios da diligência | B5: =Diligencia!B28 | C5: Qualquer bloqueio ativo impede lance
A6: Comparáveis suficientes | B6: =IF(Comparaveis!B17>=5,"SIM","NÃO") | C6: Mínimo 5
A7: Débitos pendentes | B7: =IF(Debitos!B16=0,"SIM","NÃO") | C7: Devem estar apurados ou formalmente cobertos
A8: Lance dentro do máximo | B8: =IF(Entradas!B14<=Fluxo!B33,"SIM","NÃO") | C8: Arrematação ≤ lance máximo
A9: Liberação geral | B9: =IF(AND(B5=0,B6="SIM",B7="SIM",B8="SIM"),"LIBERADO","BLOQUEADO") | C9: Todos os critérios acima atendidos
A11: PONTUAÇÃO — SOMENTE APÓS LIBERAÇÃO
A12: Critério | B12: Peso | C12: Pontos | D12: Regra resumida
A13: Desconto sobre mercado | B13: 20 | C13: =IF(Fluxo!B27>=0.4,20,IF(Fluxo!B27>=0.3,15,IF(Fluxo!B27>=0.2,8,0))) | D13: >=40%=20; >=30%=15; >=20%=8
A14: ROI anualizado | B14: 20 | C14: =IF(Fluxo!B30>=0.3,20,IF(Fluxo!B30>=0.2,15,IF(Fluxo!B30>=Entradas!B29,8,0))) | D14: >=30%=20; >=20%=15; >=TMA=8
A15: Ocupação / posse | B15: 15 | C15: =IF(Cenarios!E6<=1,15,IF(Cenarios!E6<=4,10,IF(Cenarios!E6<=8,5,0))) | D15: Prazo até posse: <=1=15; <=4=10; <=8=5
A16: Ônus e débitos | B16: 15 | C16: =IF(AND(Debitos!B16=0,Diligencia!B27=0),15,0) | D16: Sem pendência=15; caso contrário 0
A17: Conservação / reforma | B17: 10 | C17: =IF(Cenarios!E9/Fluxo!B6<=0.05,10,IF(Cenarios!E9/Fluxo!B6<=0.1,7,IF(Cenarios!E9/Fluxo!B6<=0.2,3,0))) | D17: Reforma / venda: <=5%=10; <=10%=7; <=20%=3
A18: Liquidez / prazo de venda | B18: 10 | C18: =IF(Cenarios!E8<=3,10,IF(Cenarios!E8<=6,7,IF(Cenarios!E8<=9,4,0))) | D18: <=3m=10; <=6m=7; <=9m=4
A19: Confiança de mercado | B19: 10 | C19: =IF(Comparaveis!B17>=5,10,IF(Comparaveis!B17>=3,5,0)) | D19: 5+ comparáveis=10; 3-4=5
A20: TOTAL | B20: 100 | C20: =SUM(C13:C19)
A21: CLASSIFICAÇÃO | C21: =IF(B9="BLOQUEADO","VERMELHO - BLOQUEADO",IF(C20>=80,"VERDE",IF(C20>=60,"AMARELO","VERMELHO")))

Sheet Dashboard
A1: DASHBOARD EXECUTIVO — DECISÃO DE ARREMATAÇÃO
A3: DECISÃO
A4: =Score!C21 | E4: =IF(Score!B9="BLOQUEADO","NÃO DAR LANCE","LANCE MÁXIMO: "&TEXT(Fluxo!B33,"R$ #,##0")) | I4: =Fluxo!B34
A10: INDICADORES FINANCEIROS
A11: Indicador | B11: Valor | C11: Meta | D11: Status | E11: Indicador | F11: Valor | G11: Meta | H11: Status
A12: Valor de mercado | B12: =Fluxo!B5 | C12: Validado | E12: Investimento total | F12: =Fluxo!B19
A13: Preço de arrematação | B13: =Entradas!B14 | C13: ≤ lance máx. | E13: Lucro líquido | F13: =Fluxo!B22 | G13: > 0
A14: Desconto bruto | B14: =Fluxo!B27 | C14: >=30% | E14: ROI total | F14: =Fluxo!B29 | G14: >=20%
A15: Prazo total | B15: =Fluxo!B26 | C15: ≤12 meses | E15: ROI anualizado | F15: =Fluxo!B30 | G15: >=TMA
A16: Lance máximo | B16: =Fluxo!B33 | E16: Margem líquida | F16: =Fluxo!B28 | G16: >=15%
A18: RISCOS E PENDÊNCIAS
A19: Indicador | B19: Resultado | C19: Leitura | D19: Indicador | E19: Resultado | F19: Leitura
A20: Bloqueios ativos | B20: =Diligencia!B28 | C20: Deve ser zero | D20: Críticos pendentes | E20: =Diligencia!B26 | F20: Deve ser zero
A21: Críticos com problema | B21: =Diligencia!B27 | C21: Deve ser zero | D21: Débitos pendentes | E21: =Debitos!B16 | F21: Deve ser zero
A22: Comparáveis usados | B22: =Comparaveis!B17 | C22: Mínimo 5 | D22: Score | E22: =Score!C20 | F22: Somente após liberação
A23: Cenário selecionado | B23: =Entradas!B10 | D23: Prazo até posse | E23: =Cenarios!E6 | F23: meses
A24: Reforma selecionada | B24: =Cenarios!E9 | D24: Prazo de venda | E24: =Cenarios!E8 | F24: meses
A26: PRÓXIMAS AÇÕES PRIORITÁRIAS
A27: 1. Validar juridicamente a penhora e a baixa do ônus.
A28: 2. Obter saldo atualizado do condomínio e certidão de IPTU.
A29: 3. Confirmar ocupação e realizar visita técnica.
A30: 4. Inserir pelo menos cinco comparáveis reais.
A31: 5. Confirmar capital disponível e respeitar o lance máximo.
